genome_reader/__init__.py
genome_reader/genome.py
genome_reader/genotype.py
genome_reader/snp.py
genome_reader/version.py
genome_reader/tests/__init__.py
genome_reader/tests/conftest.py
genome_reader/tests/test.txt
genome_reader/tests/test_genome.py
genome_reader-0.1.1.data/scripts/genome
genome_reader-0.1.1.dist-info/LICENSE
genome_reader-0.1.1.dist-info/METADATA
genome_reader-0.1.1.dist-info/WHEEL
genome_reader-0.1.1.dist-info/top_level.txt
genome_reader-0.1.1.dist-info/RECORD
