Metadata-Version: 2.1
Name: genome-reader
Version: 0.1.1
Summary: genome reader
Home-page: https://github.com/marigenhq/genome-reader
Author: Gary Lai
Author-email: gary.lai@marigen.us
License: MIT
Download-URL: https://github.com/marigenhq/genome-reader/tree/master
Keywords: genome reader
Platform: UNKNOWN
Classifier: Development Status :: 3 - Alpha
Classifier: Intended Audience :: Science/Research
Classifier: Intended Audience :: Developers
Classifier: License :: OSI Approved :: Apache Software License
Classifier: Programming Language :: Python :: 3 :: Only
Classifier: Programming Language :: Python :: 3.4
Classifier: Programming Language :: Python :: 3.5
Classifier: Programming Language :: Python :: 3.6
Classifier: Programming Language :: Python :: 3.7
Classifier: Programming Language :: Python :: 3.8
Classifier: Topic :: Scientific/Engineering :: Artificial Intelligence
Classifier: Topic :: Scientific/Engineering :: Information Analysis
Classifier: Operating System :: POSIX
Classifier: Operating System :: Unix
Classifier: Operating System :: MacOS
Requires-Dist: typing (==3.6.6)
